Workbook

Sheet Übersicht
A3: Gesamt | C3: Einnahmen | D3: Ausgaben | E3: mtl. Überschuss (kalt) | F3: Nebenkostenvorauszahlung | G3: Vermögenszuwachs | H3: zu versteuern
C6: =Einnahmen!C3 -> 5560 | D6: =Ausgaben!C3 -> 5305.6767 | E6: ='mtl. Überschuss'!C3 -> 344.32 | F6: =Nebekostenvorauszahlung!C3 -> -89.996667 | G6: ='Vermögenszuwachs'!C3 -> 1950.64
C9: =C6-D6 -> 254.32333
A13: Wohneinheiten | C13: Einnahmen | D13: Ausgaben | E13: mtl. Überschuss | F13: Nebenkostenvorauszahlung | G13: Vermögenszuwachs
A16: Arndtstr. 115 / WE 7 / 39m² / 20.000€ | C16: =Einnahmen!C12 -> 530 | D16: =Ausgaben!C13 -> 252.74 | E16: ='mtl. Überschuss'!C9 -> 281 | F16: =Nebekostenvorauszahlung!C9 -> -3.74 | G16: ='Vermögenszuwachs'!C9 -> 281
A19: Friedrichstr. 8 / WE 11 / 46m² / 59.000€ | C19: =Einnahmen!C15 -> 610 | D19: =Ausgaben!C16 -> 534.14 | E19: ='mtl. Überschuss'!C12 -> 59.58 | F19: =Nebekostenvorauszahlung!C12 -> 16.28 | G19: ='Vermögenszuwachs'!C12 -> 245
A22: Dülmener Str. 19 / 78m² / 65.000€ | C22: =Einnahmen!C18 -> 700 | D22: =Ausgaben!C19 -> 676.06 | E22: ='mtl. Überschuss'!C15 -> 40.67 | F22: =Nebekostenvorauszahlung!C15 -> -16.73 | G22: ='Vermögenszuwachs'!C15 -> 394.62
A25: Friedrichstr. 8 / WE 14 / 46m² / 65.000€ | C25: =Einnahmen!C21 -> 650 | D25: =Ausgaben!C22 -> 565.06 | E25: ='mtl. Überschuss'!C18 -> 106.77 | F25: =Nebekostenvorauszahlung!C18 -> -21.83 | G25: ='Vermögenszuwachs'!C18 -> 271.77
A28: Friedrichstr.6 / WE 01 / 48m² / 55.000€ | C28: =Einnahmen!C24 -> 510 | D28: =Ausgaben!C25 -> 505.73 | E28: ='mtl. Überschuss'!C21 -> 10.5 | F28: =Nebekostenvorauszahlung!C21 -> -6.23 | G28: ='Vermögenszuwachs'!C21 -> 151.5
A31: Körnerstr 43 / 44m² / 53.000€ + Carport | C31: =Einnahmen!C27 -> 0 | D31: =Ausgaben!C28 -> 315 | E31: ='mtl. Überschuss'!C24 -> -315 | F31: =Nebekostenvorauszahlung!C24 -> 0 | G31: ='Vermögenszuwachs'!C24 -> -215
A34: Hörder Phönixseeallee 152 / WE 3 / 39m² / 91.250€ | C34: =Einnahmen!C30 -> 400 | D34: =Ausgaben!C31 -> 599.2775 | E34: ='mtl. Überschuss'!C27 -> -212.28 | F34: =Nebekostenvorauszahlung!C27 -> 13.0025 | G34: ='Vermögenszuwachs'!C27 -> -28.76
A37: Hörder Phönixseeallee 152 / WE 4 / 37m² / 91.250€ | C37: =Einnahmen!C33 -> 600 | D37: =Ausgaben!C34 -> 597.6675 | E37: ='mtl. Überschuss'!C30 -> -5.02 | F37: =Nebekostenvorauszahlung!C30 -> 7.3525 | G37: ='Vermögenszuwachs'!C30 -> 178.5
A40: Arndtstr. 115 / WE 05 / 43m² / 40.000€ | C40: =Einnahmen!C36 -> 510 | D40: =Ausgaben!C37 -> 708.47833 | E40: ='mtl. Überschuss'!C33 -> -166.9 | F40: =Nebekostenvorauszahlung!C33 -> -31.578333 | G40: ='Vermögenszuwachs'!C33 -> 127.01
A43: Hohenstein 62, WE 9, 50m², 42283 Wuppertal | C43: =Einnahmen!C39 -> 500 | D43: =Ausgaben!C40 -> 245.76167 | E43: ='mtl. Überschuss'!C36 -> 251 | F43: =Nebekostenvorauszahlung!C36 -> 3.2383333 | G43: ='Vermögenszuwachs'!C36 -> 251
A46: Goldhammerstr. 46, WE 7, 38m², 44793 Bochum | C46: =Einnahmen!C42 -> 550 | D46: =Ausgaben!C43 -> 305.76167 | E46: ='mtl. Überschuss'!C39 -> 294 | F46: =Nebekostenvorauszahlung!C39 -> -49.761667 | G46: ='Vermögenszuwachs'!C39 -> 294

Sheet Einnahmen
A1: Einnahmen
A3: Gesamt | C3: =SUM(D6:E6) -> 5560
D6: =SUM(D12:D43)+SUM(F12:F1003) -> 3999.35 | E6: =SUM(E8:E53) -> 1560.65
C9: Ges. Miete | D9: Kaltmiete | E9: Nebenkosten | F9: Weitere Einnahmen
A12: Arndtstr. 115 / WE 7 / 41m² / 20.000€ | C12: =D12+E12+F12 -> 530 | D12: 370 | E12: 160
A15: Friedrichstr. 8 / WE 11 / 46m² / 59.000€ | C15: =D15+E15+F15 -> 610 | D15: 390 | E15: 220
A18: Dülmener Str. 19 / 78m² / 65.000€ | C18: =D18+E18+F18 -> 700 | D18: 500 | E18: 200
A21: Friedrichstr. 8 / WE 14 / 46m² / 65.000€ | C21: =D21+E21+F21 -> 650 | D21: 449.35 | E21: 200.65
A24: Friedrichstr.6 / WE 01 / 47m² / 55.000€ | C24: =D24+E24+F24 -> 510 | D24: 320 | E24: 190
A27: Körnerstr 43 / 44m² / 53.000€ + Carport | C27: =D27+E27+F27 -> 0 | D27: 0 | E27: 0 | F27: 0
A30: Hörder Phönixseeallee 152 / WE 3 / 39m² / 91.250€ | C30: =D30+E30+F30 -> 400 | D30: 313 | E30: 87
A33: Hörder Phönixseeallee 152 / WE 4 / 37m² / 91.250€ | C33: =D33+E33+F33 -> 600 | D33: 520 | E33: 80
A36: Arndtstr. 115 / WE 05 / 46m² / 40.000€ | C36: =D36+E36+F36 -> 510 | D36: 377 | E36: 133 | F36: 0
A39: Hohenstein 62, WE 9, 50m², 42283 Wuppertal | C39: =SUM(D39:E39) -> 500 | D39: 360 | E39: 140
A42: Goldhammerstr. 46, WE 7, 38m², 44793 Bochum | C42: =SUM(D42:E42) -> 550 | D42: 400 | E42: 150

Sheet Ausgaben
A1: Ausgaben
A3: Gesamt | C3: =SUM(D6:L6) -> 5305.6767
D6: =SUM(D8:D155) -> 2836.17 | I6: =SUM(I8:I150) -> 2286.76 | L6: =SUM(L8:L150) -> 182.74667
A9: Wohneinheiten | C9: Gesamt | D9: Kredit | I9: Hausverwaltung | L9: Grundsteuer
D11: Gesamt | E11: Tilgung 1 | F11: Zinsen 1 | G11: Tilgung 2 | H11: Zinsen 2 | I11: Gesamt | J11: n. umlegbar | K11: umlegbar
A13: Arndtstr. 115 / WE 7 / 39m² / 20.000€ | C13: =D13+I13+L13 -> 252.74 | D13: =E13+F13+G13+H13 -> 0 | E13: 0 | F13: 0 | G13: 0 | H13: 0 | I13: =J13+K13 -> 244 | J13: 89 | K13: 155 | L13: 8.74
A16: Friedrichstr. 8 / WE 11 / 46m² / 59.000€ | C16: =D16+I16+L16 -> 534.14 | D16: =E16+F16+G16+H16 -> 220.42 | E16: 185.42 | F16: 35 | G16: 0 | H16: 0 | I16: =J16+K16 -> 302 | J16: 110 | K16: 192 | L16: 11.72
A19: Dülmener Str. 19 / 78m² / 65.000€ | C19: =D19+I19+L19 -> 676.06 | D19: =E19+F19+G19+H19 -> 437.33 | E19: 170 | F19: 57.75 | G19: 183.95 | H19: 25.63 | I19: =J19+K19 -> 222 | J19: 22 | K19: 200 | L19: 16.73
A22: Friedrichstr. 8 / WE 14 / 46m² / 65.000€ | C22: =D22+I22+L22 -> 565.06 | D22: =E22+F22+G22+H22 -> 228.58 | E22: 165 | F22: 63.58 | G22: 0 | H22: 0 | I22: =J22+K22 -> 281 | J22: 114 | K22: 167 | L22: 55.48
A25: Friedrichstr.6 / WE 01 / 48m² / 55.000€ | C25: =D25+I25+L25 -> 505.73 | D25: =E25+F25+G25+H25 -> 195.5 | E25: 141 | F25: 54.5 | G25: 0 | H25: 0 | I25: =J25+K25 -> 298 | J25: 114 | K25: 184 | L25: 12.23
A28: Körnerstr 43 / 44m² / 53.000€ + Carport | C28: =D28+I28+L28 -> 315 | D28: =E28+F28+G28+H28 -> 315 | E28: 100 | F28: 215 | G28: 0 | H28: 0 | I28: =J28+K28 -> 0 | J28: 0 | K28: 0 | L28: 0
A31: Hörder Phönixseeallee 152 / WE 3 / 39m² / 91.250€ | C31: =D31+I31+L31 -> 599.2775 | D31: =E31+F31+G31+H31 -> 495.22 | E31: 131.25 | F31: 285 | G31: 52.27 | H31: 26.7 | I31: =J31+K31 -> 86.25 | J31: 30.06 | K31: 56.19 | L31: =213.69/12 -> 17.8075
A34: Hörder Phönixseeallee 152 / WE 4 / 37m² / 91.250€ | C34: =D34+I34+L34 -> 597.6675 | D34: =E34+F34+G34+H34 -> 495.22 | E34: 131.25 | F34: 285 | G34: 52.27 | H34: 26.7 | I34: =J34+K34 -> 85.51 | J34: 29.8 | K34: 55.71 | L34: =203.25/12 -> 16.9375
A37: Arndtstr. 115 / WE 05 / 43m² / 40.000€ | C37: =D37+I37+L37 -> 708.47833 | D37: =E37+F37+G37+H37 -> 448.9 | E37: 174.37 | F37: 85 | G37: 119.54 | H37: 69.99 | I37: =J37+K37 -> 250 | J37: 95 | K37: 155 | L37: =114.94/12 -> 9.5783333
A40: Hohenstein 62, WE 9, 50m², 42283 Wuppertal | C40: =D40+I40+L40 -> 245.76167 | D40: =E40+F40+G40+H40 -> 0 | E40: 0 | F40: 0 | G40: 0 | H40: 0 | I40: =J40+K40 -> 229 | J40: 109 | K40: 120 | L40: =201.14/12 -> 16.761667
A43: Goldhammerstr. 46, WE 7, 38m², 44793 Bochum | C43: =D43+I43+L43 -> 305.76167 | D43: =E43+F43+G43+H43 -> 0 | G43: 0 | H43: 0 | I43: =J43+K43 -> 289 | J43: 106 | K43: 183 | L43: =201.14/12 -> 16.761667

Sheet mtl. Überschuss
A1: mtl. Überschuss kalt (alle Kosten Tilgung & Zinsen & nicht umlegbare Kosten abgezogen)
A3: Gesamt | C3: =SUM(C9:C50) -> 344.32
A6: Wohneinheiten | C6: Gesamt | D6: Kaltimiete | E6: mtl. Betriebskosten n. umlegbar | F6: Tilgung | G6: Zinsen
A9: Arndtstr. 115 / WE 7 / 39m² / 20.000€ | C9: =D9-E9-F9-G9 -> 281 | D9: =Einnahmen!D12+Einnahmen!F12 -> 370 | E9: =Ausgaben!J13 -> 89 | F9: =Ausgaben!E13+Ausgaben!G13 -> 0 | G9: =Ausgaben!F13+Ausgaben!H13 -> 0
A12: Friedrichstr. 8 / WE 11 / 46m² / 59.000€ | C12: =D12-E12-F12-G12 -> 59.58 | D12: =Einnahmen!D15+Einnahmen!F15 -> 390 | E12: =Ausgaben!J16 -> 110 | F12: =Ausgaben!E16+Ausgaben!G16 -> 185.42 | G12: =Ausgaben!F16+Ausgaben!H16 -> 35
A15: Dülmener Str. 19 / 78m² / 65.000€ | C15: =D15-E15-F15-G15 -> 40.67 | D15: =Einnahmen!D18+Einnahmen!F18 -> 500 | E15: =Ausgaben!J19 -> 22 | F15: =Ausgaben!E19+Ausgaben!G19 -> 353.95 | G15: =Ausgaben!F19+Ausgaben!H19 -> 83.38
A18: Friedrichstr. 8 / WE 14 / 46m² / 65.000€ | C18: =D18-E18-F18-G18 -> 106.77 | D18: =Einnahmen!D21+Einnahmen!F21 -> 449.35 | E18: =Ausgaben!J22 -> 114 | F18: =Ausgaben!E22+Ausgaben!G22 -> 165 | G18: =Ausgaben!F22+Ausgaben!H22 -> 63.58
A21: Friedrichstr.6 / WE 01 / 48m² / 55.000€ | C21: =D21-E21-F21-G21 -> 10.5 | D21: =Einnahmen!D24+Einnahmen!F24 -> 320 | E21: =Ausgaben!J25 -> 114 | F21: =Ausgaben!E25+Ausgaben!G25 -> 141 | G21: =Ausgaben!F25+Ausgaben!H25 -> 54.5
A24: Körnerstr 43 / 44m² / 53.000€ + Carport | C24: =D24-E24-F24-G24 -> -315 | D24: =Einnahmen!D27+Einnahmen!F27 -> 0 | E24: =Ausgaben!J28 -> 0 | F24: =Ausgaben!E28+Ausgaben!G28 -> 100 | G24: =Ausgaben!F28+Ausgaben!H28 -> 215
A27: Hörder Phönixseeallee 152 / WE 3 / 39m² / 91.250€ | C27: =D27-E27-F27-G27 -> -212.28 | D27: =Einnahmen!D30+Einnahmen!F30 -> 313 | E27: =Ausgaben!J31 -> 30.06 | F27: =Ausgaben!E31+Ausgaben!G31 -> 183.52 | G27: =Ausgaben!F31+Ausgaben!H31 -> 311.7
A30: Hörder Phönixseeallee 152 / WE 4 / 37m² / 91.250€ | C30: =D30-E30-F30-G30 -> -5.02 | D30: =Einnahmen!D33+Einnahmen!F33 -> 520 | E30: =Ausgaben!J34 -> 29.8 | F30: =Ausgaben!E34+Ausgaben!G34 -> 183.52 | G30: =Ausgaben!F34+Ausgaben!H34 -> 311.7
A33: Arndtstr. 115 / WE 05 / 43m² / 40.000€ | C33: =D33-E33-F33-G33 -> -166.9 | D33: =Einnahmen!D36+Einnahmen!F36 -> 377 | E33: =Ausgaben!J37 -> 95 | F33: =Ausgaben!E37+Ausgaben!G37 -> 293.91 | G33: =Ausgaben!F37+Ausgaben!H37 -> 154.99
A36: Hohenstein 62, WE 9, 50m², 42283 Wuppertal | C36: =D36-E36-F36-G36 -> 251 | D36: =Einnahmen!D39+Einnahmen!F39 -> 360 | E36: =Ausgaben!J40 -> 109 | F36: =Ausgaben!E40+Ausgaben!G40 -> 0 | G36: =Ausgaben!F40+Ausgaben!H40 -> 0
A39: Goldhammerstr. 46, WE 7, 38m², 44793 Bochum | C39: =D39-E39-F39-G39 -> 294 | D39: =Einnahmen!D42+Einnahmen!F42 -> 400 | E39: =Ausgaben!J43 -> 106 | F39: =Ausgaben!E43+Ausgaben!G43 -> 0 | G39: =Ausgaben!F43+Ausgaben!H43 -> 0

Sheet Vermögenszuwachs
A1: Vermögenszuwachs (zu versteuern)
A3: Gesamt | C3: =SUM(C9:C50) -> 1950.64
A6: Wohneinheiten | C6: Gesamt p.m. | D6: Kaltmiete + Stellplatz | E6: Zinsen | F6: n. umlegbare Kosten
A9: Arndtstr. 115 / WE 7 / 39m² / 20.000€ | C9: =D9-E9-F9 -> 281 | D9: =Einnahmen!D12+Einnahmen!F12 -> 370 | E9: =Ausgaben!F13+Ausgaben!H13 -> 0 | F9: =Ausgaben!J13 -> 89
A12: Friedrichstr. 8 / WE 11 / 46m² / 59.000€ | C12: =D12-E12-F12 -> 245 | D12: =Einnahmen!D15+Einnahmen!F15 -> 390 | E12: =Ausgaben!F16+Ausgaben!H16 -> 35 | F12: =Ausgaben!J16 -> 110
A15: Dülmener Str. 19 / 78m² / 65.000€ | C15: =D15-E15-F15 -> 394.62 | D15: =Einnahmen!D18+Einnahmen!F18 -> 500 | E15: =Ausgaben!F19+Ausgaben!H19 -> 83.38 | F15: =Ausgaben!J19 -> 22
A18: Friedrichstr. 8 / WE 14 / 46m² / 65.000€ | C18: =D18-E18-F18 -> 271.77 | D18: =Einnahmen!D21+Einnahmen!F21 -> 449.35 | E18: =Ausgaben!F22+Ausgaben!H22 -> 63.58 | F18: =Ausgaben!J22 -> 114
A21: Friedrichstr.6 / WE 01 / 48m² / 55.000€ | C21: =D21-E21-F21 -> 151.5 | D21: =Einnahmen!D24+Einnahmen!F24 -> 320 | E21: =Ausgaben!F25+Ausgaben!H25 -> 54.5 | F21: =Ausgaben!J25 -> 114
A24: Körnerstr 43 / 44m² / 53.000€ + Carport | C24: =D24-E24-F24 -> -215 | D24: =Einnahmen!D27+Einnahmen!F27 -> 0 | E24: =Ausgaben!F28+Ausgaben!H28 -> 215 | F24: =Ausgaben!J28 -> 0
A27: Hörder Phönixseeallee 152 / WE 3 / 39m² / 91.250€ | C27: =D27-E27-F27 -> -28.76 | D27: =Einnahmen!D30+Einnahmen!F30 -> 313 | E27: =Ausgaben!F31+Ausgaben!H31 -> 311.7 | F27: =Ausgaben!J31 -> 30.06
A30: Hörder Phönixseeallee 152 / WE 4 / 37m² / 91.250€ | C30: =D30-E30-F30 -> 178.5 | D30: =Einnahmen!D33+Einnahmen!F33 -> 520 | E30: =Ausgaben!F34+Ausgaben!H34 -> 311.7 | F30: =Ausgaben!J34 -> 29.8
A33: Arndtstr. 115 / WE 05 / 43m² / 40.000€ | C33: =D33-E33-F33 -> 127.01 | D33: =Einnahmen!D36+Einnahmen!F36 -> 377 | E33: =Ausgaben!F37+Ausgaben!H37 -> 154.99 | F33: =Ausgaben!J37 -> 95
A36: Hohenstein 62 / WE 9 / 50m² / 35.000€ | C36: =D36-E36-F36 -> 251 | D36: =Einnahmen!D39+Einnahmen!F39 -> 360 | E36: =Ausgaben!F40+Ausgaben!H40 -> 0 | F36: =Ausgaben!J40 -> 109
A39: Goldhammerstr. 46, WE 7, 38m², 44793 Bochum | C39: =D39-E39-F39 -> 294 | D39: =Einnahmen!D42+Einnahmen!F42 -> 400 | E39: =Ausgaben!F43+Ausgaben!H43 -> 0 | F39: =Ausgaben!J43 -> 106

Sheet Steuern
A1: Steuern mtl.
A3: Gesamt | C3: =SUM(C13:C50) -> 464.015
C6: =SUM(C13:C50) -> 464.015 | E6: =SUM(E13:E50) -> 2048.71 | F6: =SUM(F13:F50)+SUM(G13:G50) -> 1229.85 | H6: =SUM(H13:H50) -> 818.86 | I6: =SUM(I13:I50) -> 1486.625
A9: Wohneinheiten | C9: zu versteuern (inkl Abschreibung) | D9: Kaltmiete + Stellplatz | E9: Gesamt | F9: Zinsen1 | G9: Zinsen 2 | H9: nicht umlegbare Betriebskosten | I9: Abschreibung
A13: Arndtstr. 115 / WE 7 / 39m² / 20.000€ | C13: =D13-E13-I13 -> 244.75 | D13: =Einnahmen!D12+Einnahmen!F12 -> 370 | E13: =F13+G13+H13 -> 89 | F13: =Ausgaben!F13 -> 0 | G13: =Ausgaben!H13 -> 0 | H13: =Ausgaben!J13 -> 89 | I13: =Abschreibung!C14/12 -> 36.25
A16: Friedrichstr. 8 / WE 11 / 46m² / 59.000€ | C16: =D16-E16-I16 -> 163.33333 | D16: =Einnahmen!D15+Einnahmen!F15 -> 390 | E16: =F16+G16+H16 -> 145 | F16: =Ausgaben!F16 -> 35 | G16: =Ausgaben!H16 -> 0 | H16: =Ausgaben!J16 -> 110 | I16: =Abschreibung!C17/12 -> 81.666667
A19: Dülmener Str. 19 / 78m² / 65.000€ | C19: =D19-E19-I19 -> 301.03667 | D19: =Einnahmen!D18+Einnahmen!F18 -> 500 | E19: =F19+G19+H19 -> 105.38 | F19: =Ausgaben!F19 -> 57.75 | G19: =Ausgaben!H19 -> 25.63 | H19: =Ausgaben!J19 -> 22 | I19: =Abschreibung!C20/12 -> 93.583333
A22: Friedrichstr. 8 / WE 14 / 46m² / 65.000€ | C22: =D22-E22-I22 -> 134.68667 | D22: =Einnahmen!D21+Einnahmen!F21 -> 449.35 | E22: =F22+G22+H22 -> 177.58 | F22: =Ausgaben!F22 -> 63.58 | G22: =Ausgaben!H22 -> 0 | H22: =Ausgaben!J22 -> 114 | I22: =Abschreibung!C23/12 -> 137.08333
A25: Friedrichstr.6 / WE 01 / 48m² / 55.000€ | C25: =D25-E25-I25 -> 97 | D25: =Einnahmen!D24+Einnahmen!F24 -> 320 | E25: =F25+G25+H25 -> 168.5 | F25: =Ausgaben!F25 -> 54.5 | G25: =Ausgaben!H25 -> 0 | H25: =Ausgaben!J25 -> 114 | I25: =Abschreibung!C26/12 -> 54.5
A28: Körnerstr 43 / 44m² / 53.000€ + Carport | C28: =D28-E28-I28 -> -301.66667 | D28: =Einnahmen!D27+Einnahmen!F27 -> 0 | E28: =F28+G28+H28 -> 215 | F28: =Ausgaben!F28 -> 215 | G28: =Ausgaben!H28 -> 0 | H28: =Ausgaben!J28 -> 0 | I28: =Abschreibung!C29/12 -> 86.666667
A31: Hörder Phönixseeallee 152 / WE 3 / 39m² / 91.250€ | C31: =D31-E31-I31 -> -471.46833 | D31: =Einnahmen!D30+Einnahmen!F30 -> 313 | E31: =F31+G31+H31 -> 341.76 | F31: =Ausgaben!F31 -> 285 | G31: =Ausgaben!H31 -> 26.7 | H31: =Ausgaben!J31 -> 30.06 | I31: =Abschreibung!C32/12 -> 442.70833
A34: Hörder Phönixseeallee 152 / WE 4 / 37m² / 91.250€ | C34: =D34-E34-I34 -> -259 | D34: =Einnahmen!D33+Einnahmen!F33 -> 520 | E34: =F34+G34+H34 -> 341.5 | F34: =Ausgaben!F34 -> 285 | G34: =Ausgaben!H34 -> 26.7 | H34: =Ausgaben!J34 -> 29.8 | I34: =Abschreibung!C35/12 -> 437.5
A37: Arndtstr. 115 / WE 05 / 43m² / 40.000€ | C37: =D37-E37-I37 -> 85.343333 | D37: =Einnahmen!D36+Einnahmen!F36 -> 377 | E37: =F37+G37+H37 -> 249.99 | F37: =Ausgaben!F37 -> 85 | G37: =Ausgaben!H37 -> 69.99 | H37: =Ausgaben!J37 -> 95 | I37: =Abschreibung!C38/12 -> 41.666667
A40: Hohenstein 62, WE 9, 50m², 42283 Wuppertal | C40: =D40-E40-I40 -> 204.33333 | D40: =Einnahmen!D39+Einnahmen!F39 -> 360 | E40: =F40+G40+H40 -> 109 | F40: =Ausgaben!F40 -> 0 | G40: =Ausgaben!H40 -> 0 | H40: =Ausgaben!J40 -> 109 | I40: =Abschreibung!C41/12 -> 46.666667
A43: Goldhammerstr. 46, WE 7, 38m², 44793 Bochum | C43: =D43-E43-I43 -> 265.66667 | D43: =Einnahmen!D42+Einnahmen!F42 -> 400 | E43: =F43+G43+H43 -> 106 | F43: =Ausgaben!F43 | G43: =Ausgaben!H43 -> 0 | H43: =Ausgaben!J43 -> 106 | I43: =Abschreibung!C44/12 -> 28.333333

Sheet Nebekostenvorauszahlung
A1: Nebenkostenvorrauszahlung
A3: Gesamt | C3: =SUM(C9:C50) -> -89.996667 | G3: Minus Nachzahlung von Mieter / Plus Guthaben Mieter
A6: Wohneinheiten | C6: Gesamt | D6: Betriebskosten | E6: umlagefähig | F6: Grundsteuer
A9: Arndtstr. 115 / WE 7 / 39m² / 20.000€ | C9: =D9-E9-F9 -> -3.74 | D9: =Einnahmen!E12 -> 160 | E9: =Ausgaben!K13 -> 155 | F9: =Ausgaben!L13 -> 8.74
A12: Friedrichstr. 8 / WE 11 / 46m² / 59.000€ | C12: =D12-E12-F12 -> 16.28 | D12: =Einnahmen!E15 -> 220 | E12: =Ausgaben!K16 -> 192 | F12: =Ausgaben!L16 -> 11.72
A15: Dülmener Str. 19 / 78m² / 65.000€ | C15: =D15-E15-F15 -> -16.73 | D15: =Einnahmen!E18 -> 200 | E15: =Ausgaben!K19 -> 200 | F15: =Ausgaben!L19 -> 16.73
A18: Friedrichstr. 8 / WE 14 / 46m² / 65.000€ | C18: =D18-E18-F18 -> -21.83 | D18: =Einnahmen!E21 -> 200.65 | E18: =Ausgaben!K22 -> 167 | F18: =Ausgaben!L22 -> 55.48
A21: Friedrichstr.6 / WE 01 / 48m² / 55.000€ | C21: =D21-E21-F21 -> -6.23 | D21: =Einnahmen!E24 -> 190 | E21: =Ausgaben!K25 -> 184 | F21: =Ausgaben!L25 -> 12.23
A24: Körnerstr 43 / 44m² / 53.000€ + Carport | C24: =D24-E24-F24 -> 0 | D24: =Einnahmen!E27 -> 0 | E24: =Ausgaben!K28 -> 0 | F24: =Ausgaben!L28 -> 0
A27: Hörder Phönixseeallee 152 / WE 3 / 39m² / 91.250€ | C27: =D27-E27-F27 -> 13.0025 | D27: =Einnahmen!E30 -> 87 | E27: =Ausgaben!K31 -> 56.19 | F27: =Ausgaben!L31 -> 17.8075
A30: Hörder Phönixseeallee 152 / WE 4 / 37m² / 91.250€ | C30: =D30-E30-F30 -> 7.3525 | D30: =Einnahmen!E33 -> 80 | E30: =Ausgaben!K34 -> 55.71 | F30: =Ausgaben!L34 -> 16.9375
A33: Arndtstr. 115 / WE 05 / 43m² / 40.000€ | C33: =D33-E33-F33 -> -31.578333 | D33: =Einnahmen!E36 -> 133 | E33: =Ausgaben!K37 -> 155 | F33: =Ausgaben!L37 -> 9.5783333
A36: Hohenstein 62, WE 9, 50m², 42283 Wuppertal | C36: =D36-E36-F36 -> 3.2383333 | D36: =Einnahmen!E39 -> 140 | E36: =Ausgaben!K40 -> 120 | F36: =Ausgaben!L40 -> 16.761667
A39: Goldhammerstr. 46, WE 7, 38m², 44793 Bochum | C39: =D39-E39-F39 -> -49.761667 | D39: =Einnahmen!E42 -> 150 | E39: =Ausgaben!K43 -> 183 | F39: =Ausgaben!L43 -> 16.761667

Sheet Tilgung
A1: Tilgung
A4: Gesamt | C4: =SUM(C14:C40) -> 1606.32
D7: =SUM(D14:D50)+SUM(E14:E50) -> 1606.32
A10: Wohneinheiten | C10: Gesamt | D10: Tilgung 1 | E10: Tilgung 2
A14: Arndtstr. 115 / WE 7 / 39m² / 20.000€ | C14: =D14+E14 -> 0 | D14: =Ausgaben!E13 -> 0 | E14: =Ausgaben!G13 -> 0
A17: Friedrichstr. 8 / WE 11 / 46m² / 59.000€ | C17: =D17+E17 -> 185.42 | D17: =Ausgaben!E16 -> 185.42 | E17: =Ausgaben!G16 -> 0
A20: Dülmener Str. 19 / 78m² / 65.000€ | C20: =D20+E20 -> 353.95 | D20: =Ausgaben!E19 -> 170 | E20: =Ausgaben!G19 -> 183.95
A23: Friedrichstr. 8 / WE 14 / 46m² / 65.000€ | C23: =D23+E23 -> 165 | D23: =Ausgaben!E22 -> 165 | E23: =Ausgaben!G22 -> 0
A26: Friedrichstr.6 / WE 01 / 48m² / 55.000€ | C26: =D26+E26 -> 141 | D26: =Ausgaben!E25 -> 141 | E26: =Ausgaben!G25 -> 0
A29: Körnerstr 43 / 44m² / 53.000€ + Carport | C29: =D29+E29 -> 100 | D29: =Ausgaben!E28 -> 100 | E29: =Ausgaben!G28 -> 0
A32: Hörder Phönixseeallee 152 / WE 3 / 39m² / 91.250€ | C32: =D32+E32 -> 183.52 | D32: =Ausgaben!E31 -> 131.25 | E32: =Ausgaben!G31 -> 52.27
A35: Hörder Phönixseeallee 152 / WE 4 / 37m² / 91.250€ | C35: =D35+E35 -> 183.52 | D35: =Ausgaben!E34 -> 131.25 | E35: =Ausgaben!G34 -> 52.27
A38: Arndtstr. 115 / WE 05 / 43m² / 40.000€ | C38: =D38+E38 -> 293.91 | D38: =Ausgaben!E37 -> 174.37 | E38: =Ausgaben!G37 -> 119.54
A41: Hohenstein 62, WE 9, 50m², 42283 Wuppertal | C41: =D41+E41 -> 0 | D41: =Ausgaben!E40 -> 0 | E41: =Ausgaben!G40 -> 0
A44: Goldhammerstr. 46, WE 7, 38m², 44793 Bochum | C44: =D44+E44 -> 0 | D44: =Ausgaben!E43 | E44: =Ausgaben!G43 -> 0

Sheet Kredite
A1: Kredite
A4: Gesamt | C4: =SUM(C14:C40) -> 1606.32
D7: =SUM(D14:D50)+SUM(E14:E50) -> 1606.32
A10: Wohneinheiten | C10: Gesamt | D10: Tilgung 1 | E10: Tilgung 2
A14: Arndtstr. 115 / WE 7 / 39m² / 20.000€ | C14: =D14+E14 -> 0 | D14: =Ausgaben!E13 -> 0 | E14: =Ausgaben!G13 -> 0
A17: Friedrichstr. 8 / WE 11 / 46m² / 59.000€ | C17: =D17+E17 -> 185.42 | D17: =Ausgaben!E16 -> 185.42 | E17: =Ausgaben!G16 -> 0
A20: Dülmener Str. 19 / 78m² / 65.000€ | C20: =D20+E20 -> 353.95 | D20: =Ausgaben!E19 -> 170 | E20: =Ausgaben!G19 -> 183.95
A23: Friedrichstr. 8 / WE 14 / 46m² / 65.000€ | C23: =D23+E23 -> 165 | D23: =Ausgaben!E22 -> 165 | E23: =Ausgaben!G22 -> 0
A26: Friedrichstr.6 / WE 01 / 48m² / 55.000€ | C26: =D26+E26 -> 141 | D26: =Ausgaben!E25 -> 141 | E26: =Ausgaben!G25 -> 0
A29: Körnerstr 43 / 44m² / 53.000€ + Carport | C29: =D29+E29 -> 100 | D29: =Ausgaben!E28 -> 100 | E29: =Ausgaben!G28 -> 0
A32: Hörder Phönixseeallee 152 / WE 3 / 39m² / 91.250€ | C32: =D32+E32 -> 183.52 | D32: =Ausgaben!E31 -> 131.25 | E32: =Ausgaben!G31 -> 52.27
A35: Hörder Phönixseeallee 152 / WE 4 / 37m² / 91.250€ | C35: =D35+E35 -> 183.52 | D35: =Ausgaben!E34 -> 131.25 | E35: =Ausgaben!G34 -> 52.27
A38: Arndtstr. 115 / WE 05 / 43m² / 40.000€ | C38: =D38+E38 -> 293.91 | D38: =Ausgaben!E37 -> 174.37 | E38: =Ausgaben!G37 -> 119.54
A41: Hohenstein 62, WE 9, 50m², 42283 Wuppertal | C41: =D41+E41 -> 0 | D41: =Ausgaben!E40 -> 0 | E41: =Ausgaben!G40 -> 0
A44: Goldhammerstr. 46, WE 7, 38m², 44793 Bochum | C44: =D44+E44 -> 0 | D44: =Ausgaben!E43 | E44: =Ausgaben!G43 -> 0

Sheet Abschreibung
A1: ungefähr Abschreibung
A4: Gesamt | C4: =SUM(C14:C100) -> 17839.5
A10: Wohneinheiten | C10: Abschreibung pro Jahr | D10: Faktor Gebäude | E10: Kaufpreis | F10: Gebäude | G10: Grund / Boden | H10: Möbel + Faktor
A14: Arndtstr. 115 / WE 7 / 39m² / 20.000€ | C14: =D14*F14 -> 435 | D14: 0.025 | E14: 20000 | F14: 17400 | G14: - | H14: -
A17: Friedrichstr. 8 / WE 11 / 46m² / 59.000€ | C17: =D17*F17 -> 980 | D17: 0.02 | E17: 59000 | F17: 49000 | G17: - | H17: -
A20: Dülmener Str. 19 / 78m² / 65.000€ | C20: =D20*F20 -> 1123 | D20: 0.02 | E20: =65000 -> 65000 | F20: 56150 | G20: - | H20: -
A23: Friedrichstr. 8 / WE 14 / 46m² / 65.000€ | C23: =D23*F23+H23 -> 1645 | D23: 0.02 | E23: 65000 | F23: 52250 | G23: - | H23: =3000/5 -> 600
A26: Friedrichstr.6 / WE 01 / 48m² / 55.000€ | C26: =D26*F26 -> 654 | D26: 0.02 | E26: 55000 | F26: 32700 | G26: - | H26: -
A29: Körnerstr 43 / 44m² / 53.000€ + Carport | C29: =D29*F29+H29 -> 1040 | D29: 0.02 | E29: 53000 | F29: 42000 | G29: 10000 | H29: =1000/5 -> 200
A32: Hörder Phönixseeallee 152 / WE 3 / 39m² / 91.250€ | C32: =D32*F32+H32 -> 5312.5 | D32: 0.025 | E32: 92500 | F32: 87500 | G32: 5000 | H32: =6250/2 -> 3125
A35: Hörder Phönixseeallee 152 / WE 4 / 37m² / 91.250€ | C35: =D35*F35+H35 -> 5250 | D35: 0.025 | E35: 90000 | F35: 85000 | G35: 5000 | H35: =6250/2 -> 3125
A38: Arndtstr. 115 / WE 05 / 43m² / 40.000€ | C38: =D38*F38 -> 500 | D38: 0.025 | E38: 27000 | F38: 20000 | G38: - | H38: -
A41: Hohenstein 62, WE 9, 50m², 42283 Wuppertal | C41: =D41*F41 -> 560 | D41: 0.02 | E41: 35000 | F41: 28000 | G41: - | H41: -
A44: Goldhammerstr. 46, WE 7, 38m², 44793 Bochum | C44: =D44*F44 -> 340 | D44: 0.02 | E44: 24000 | F44: 17000 | G44: - | H44: -
